subsettools/__init__.py
subsettools/_common.py
subsettools/_constants.py
subsettools/_dev_utils.py
subsettools/_error_checking.py
subsettools/clm.py
subsettools/domain.py
subsettools/parflow_run.py
subsettools/subsetting.py
subsettools/template_runscripts/__init__.py
subsettools/template_runscripts/conus1_spinup_box.yaml
subsettools/template_runscripts/conus1_spinup_solid.yaml
subsettools/template_runscripts/conus1_transient_box.yaml
subsettools/template_runscripts/conus1_transient_solid.yaml
subsettools/template_runscripts/conus2_spinup_box.yaml
subsettools/template_runscripts/conus2_spinup_solid.yaml
subsettools/template_runscripts/conus2_transient_box.yaml
subsettools/template_runscripts/conus2_transient_solid.yaml
subsettools-2.0.9.dist-info/LICENSE
subsettools-2.0.9.dist-info/METADATA
subsettools-2.0.9.dist-info/WHEEL
subsettools-2.0.9.dist-info/RECORD
