Metadata-Version: 2.3
Name: subsettools
Version: 2.0.9
Summary: Subsetting tools and utilities for ParFlow
License: MIT
Author: George Artavanis, Amanda Triplett
Requires-Python: >=3.10,<4.0
Classifier: License :: OSI Approved :: MIT License
Classifier: Programming Language :: Python :: 3
Classifier: Programming Language :: Python :: 3.10
Classifier: Programming Language :: Python :: 3.11
Classifier: Programming Language :: Python :: 3.12
Classifier: Programming Language :: Python :: 3.13
Requires-Dist: hf-hydrodata (>=1.2.5)
Requires-Dist: numpy (>=1.23.0)
Requires-Dist: pandas (>=1.3.5)
Requires-Dist: pftools (>=1.3.10)
Requires-Dist: pylint (>=3.1.0)
Requires-Dist: requests (>=2.28.2)
